{
  "_class": "rectangle",
  "booleanOperation": 0,
  "do_objectID": "7B9FD7AD-6027-4970-A9D7-1CC2919CE59F",
  "edited": true,
  "exportOptions": {
    "_class": "exportOptions",
    "exportFormats": [
    ],
    "includedLayerIds": [
    ],
    "layerOptions": 0,
    "shouldTrim": false
  },
  "fixedRadius": 5,
  "frame": {
    "_class": "rect",
    "constrainProportions": false,
    "height": 14.27278025255896,
    "width": 2.40625,
    "x": 4.318045648968563,
    "y": -1.736885550034049
  },
  "hasConvertedToNewRoundCorners": true,
  "isFlippedHorizontal": false,
  "isFlippedVertical": false,
  "isLocked": false,
  "isVisible": true,
  "layerListExpandedType": 0,
  "name": "Rectangle 1662 Copy",
  "nameIsFixed": false,
  "path": {
    "_class": "path",
    "isClosed": true,
    "pointRadiusBehaviour": 0,
    "points": [
      {
        "_class": "curvePoint",
        "cornerRadius": 5,
        "curveFrom": "{0, 1.2043097216272884e-16}",
        "curveMode": 1,
        "curveTo": "{0, 1.2043097216272884e-16}",
        "hasCurveFrom": false,
        "hasCurveTo": false,
        "point": "{0, 1.2043097216272884e-16}"
      },
      {
        "_class": "curvePoint",
        "cornerRadius": 5,
        "curveFrom": "{1, -2.4086194432545769e-16}",
        "curveMode": 1,
        "curveTo": "{1, -2.4086194432545769e-16}",
        "hasCurveFrom": false,
        "hasCurveTo": false,
        "point": "{1, -2.4086194432545769e-16}"
      },
      {
        "_class": "curvePoint",
        "cornerRadius": 5,
        "curveFrom": "{1, 0.99999999999999978}",
        "curveMode": 1,
        "curveTo": "{1, 0.99999999999999978}",
        "hasCurveFrom": false,
        "hasCurveTo": false,
        "point": "{1, 0.99999999999999978}"
      },
      {
        "_class": "curvePoint",
        "cornerRadius": 5,
        "curveFrom": "{0, 1.0000000000000002}",
        "curveMode": 1,
        "curveTo": "{0, 1.0000000000000002}",
        "hasCurveFrom": false,
        "hasCurveTo": false,
        "point": "{0, 1.0000000000000002}"
      }
    ]
  },
  "resizingConstraint": 63,
  "resizingType": 0,
  "rotation": 495,
  "shouldBreakMaskChain": false
}